nvenn2.cp39-win_arm64.pyd
nvenn2-2.0.28.dist-info/METADATA
nvenn2-2.0.28.dist-info/WHEEL
nvenn2-2.0.28.dist-info/licenses/LICENSE
nvenn2-2.0.28.dist-info/RECORD
