Metadata-Version: 2.4
Name: nvenn2
Version: 2.0.28
Summary: Python bindings to nVenn2 to create generalized, quasi-proportional Venn diagrams
Keywords: Venn diagram,Euler diagram,generalized,proportional
Author-Email: Victor Quesada <quesadavictor@uniovi.es>
Maintainer-Email: Victor Quesada <quesadavictor@uniovi.es>
License-Expression: MIT
License-File: LICENSE
